CHANGES.txt
COPYRIGHT.txt
LICENSE.txt
README.txt
TODO.txt
setup.py
docs/Makefile
docs/changes.rst
docs/conf.py
docs/index.rst
docs/.static/logo_hi.gif
docs/.static/repoze.css
repoze/__init__.py
repoze.tm.egg-info/PKG-INFO
repoze.tm.egg-info/SOURCES.txt
repoze.tm.egg-info/dependency_links.txt
repoze.tm.egg-info/entry_points.txt
repoze.tm.egg-info/namespace_packages.txt
repoze.tm.egg-info/not-zip-safe
repoze.tm.egg-info/requires.txt
repoze.tm.egg-info/top_level.txt
repoze/tm/__init__.py
repoze/tm/tests.py